AUTHORS.rst
CONTRIBUTING.rst
HISTORY.rst
LICENSE
MANIFEST.in
README.rst
setup.cfg
setup.py
docs/Makefile
docs/README.rst
docs/authors.rst
docs/conf.py
docs/contributing.rst
docs/history.rst
docs/index.rst
docs/installation.rst
docs/make.bat
docs/readme.rst
docs/usage.rst
opyrant/__init__.py
opyrant/analysis.py
opyrant/blocks.py
opyrant/components.py
opyrant/configure.py
opyrant/errors.py
opyrant/events.py
opyrant/hwio.py
opyrant/local.py
opyrant/local_vogel.py
opyrant/local_zog.py
opyrant/opyrant.py
opyrant/panels.py
opyrant/queues.py
opyrant/reinf.py
opyrant/run_experiment.py
opyrant/states.py
opyrant/stimuli.py
opyrant/subjects.py
opyrant/trials.py
opyrant/utils.py
opyrant.egg-info/PKG-INFO
opyrant.egg-info/SOURCES.txt
opyrant.egg-info/dependency_links.txt
opyrant.egg-info/not-zip-safe
opyrant.egg-info/top_level.txt
tests/__init__.py
tests/test_opyrant.py