Metadata-Version: 1.1
Name: opyrant
Version: 0.1.3
Summary: hardware abstraction and shareable protocols for operant conditioning
Home-page: https://github.com/neuromusic/opyrant
Author: Justin Kiggins
Author-email: justin.kiggins@gmail.com
License: BSD license
Keywords: opyrant
Platform: UNKNOWN
Classifier: Development Status :: 2 - Pre-Alpha
Classifier: Intended Audience :: Developers
Classifier: License :: OSI Approved :: BSD License
Classifier: Natural Language :: English
Classifier: Programming Language :: Python :: 2
Classifier: Programming Language :: Python :: 2.6
Classifier: Programming Language :: Python :: 2.7
Classifier: Programming Language :: Python :: 3
Classifier: Programming Language :: Python :: 3.3
Classifier: Programming Language :: Python :: 3.4
Classifier: Programming Language :: Python :: 3.5
